Metadata-Version: 1.1
Name: jsc2f
Version: 0.1
Summary: Saves a JSON fields SQLs cell to a file, or UPDATE it back
Home-page: https://github.com/kylep/jsc2f
Author: Kyle Pericak
Author-email: kyle@pericak.com
License: MIT
Download-URL: https://github.com/kylep/jsc2f/archive/v0.1.tar.gz
Keywords: SQL,JSON,file
Platform: UNKNOWN
Classifier: Development Status :: 3 - Alpha
Classifier: Intended Audience :: Information Technology
Classifier: Topic :: Database
Classifier: Programming Language :: Python :: 3
Classifier: License :: OSI Approved :: MIT License
Classifier: Natural Language :: English
